[
    {
        "name": "JJ's Delivery Service",
        "videoSource": "jjds.mp4",
        "color": "#f9f2ff",
        "desc": "lol"
    },
    {
        "name": "Cube Solver",
        "videoSource": "jjds.mp4",
        "color": "#e4f5ff",
        "desc": "lol"
    },
    {
        "name": "Game of Life",
        "videoSource": "jjds.mp4",
        "color": "#feeded",
        "desc": "lol"
    },
    {
        "name": "Car Park Simulator",
        "videoSource": "jjds.mp4",
        "color": "#ecffec",
        "desc": "lol"
    }
]